odoo9_addon_purchase_packaging-9.0.1.0.0.99.dev6-py3.8-nspkg.pth
odoo_addons/purchase_packaging/README.rst
odoo_addons/purchase_packaging/__init__.py
odoo_addons/purchase_packaging/__openerp__.py
odoo_addons/purchase_packaging/hooks.py
odoo_addons/purchase_packaging/i18n/ca.po
odoo_addons/purchase_packaging/i18n/cs_CZ.po
odoo_addons/purchase_packaging/i18n/de.po
odoo_addons/purchase_packaging/i18n/es.po
odoo_addons/purchase_packaging/i18n/es_ES.po
odoo_addons/purchase_packaging/i18n/es_MX.po
odoo_addons/purchase_packaging/i18n/fi.po
odoo_addons/purchase_packaging/i18n/fr.po
odoo_addons/purchase_packaging/i18n/fr_CH.po
odoo_addons/purchase_packaging/i18n/hr.po
odoo_addons/purchase_packaging/i18n/hr_HR.po
odoo_addons/purchase_packaging/i18n/it.po
odoo_addons/purchase_packaging/i18n/nl.po
odoo_addons/purchase_packaging/i18n/nl_NL.po
odoo_addons/purchase_packaging/i18n/pt_BR.po
odoo_addons/purchase_packaging/i18n/pt_PT.po
odoo_addons/purchase_packaging/i18n/purchase_packaging.pot
odoo_addons/purchase_packaging/i18n/ro.po
odoo_addons/purchase_packaging/i18n/sk.po
odoo_addons/purchase_packaging/i18n/sl.po
odoo_addons/purchase_packaging/i18n/tr.po
odoo_addons/purchase_packaging/i18n/tr_TR.po
odoo_addons/purchase_packaging/i18n/vi_VN.po
odoo_addons/purchase_packaging/i18n/zh_CN.po
odoo_addons/purchase_packaging/models/__init__.py
odoo_addons/purchase_packaging/models/procurement_order.py
odoo_addons/purchase_packaging/models/product_supplier_info.py
odoo_addons/purchase_packaging/models/purchase_order_line.py
odoo_addons/purchase_packaging/readme/CONFIGURE.rst
odoo_addons/purchase_packaging/readme/CONTRIBUTORS.rst
odoo_addons/purchase_packaging/readme/DESCRIPTION.rst
odoo_addons/purchase_packaging/static/description/icon.png
odoo_addons/purchase_packaging/static/description/index.html
odoo_addons/purchase_packaging/tests/__init__.py
odoo_addons/purchase_packaging/tests/test_procurement_order.py
odoo_addons/purchase_packaging/tests/test_product_supplier_info.py
odoo9_addon_purchase_packaging-9.0.1.0.0.99.dev6.dist-info/METADATA
odoo9_addon_purchase_packaging-9.0.1.0.0.99.dev6.dist-info/WHEEL
odoo9_addon_purchase_packaging-9.0.1.0.0.99.dev6.dist-info/namespace_packages.txt
odoo9_addon_purchase_packaging-9.0.1.0.0.99.dev6.dist-info/top_level.txt
odoo9_addon_purchase_packaging-9.0.1.0.0.99.dev6.dist-info/RECORD
